{
    "beats": [
        {
            "time": 0.454,
            "count": 1
        },
        {
            "time": 0.714,
            "count": 1
        },
        {
            "time": 1.252,
            "count": 1
        },
        {
            "time": 1.793,
            "count": 1
        },
        {
            "time": 2.356,
            "count": 2
        },
        {
            "time": 2.877,
            "count": 1
        },
        {
            "time": 3.438,
            "count": 2
        },
        {
            "time": 3.832,
            "count": 1
        },
        {
            "time": 3.979,
            "count": 1
        },
        {
            "time": 4.534,
            "count": 2
        },
        {
            "time": 4.95,
            "count": 1
        },
        {
            "time": 5.076,
            "count": 1
        },
        {
            "time": 5.612,
            "count": 1
        },
        {
            "time": 6.159,
            "count": 1
        },
        {
            "time": 6.263,
            "count": 1
        },
        {
            "time": 6.721,
            "count": 1
        },
        {
            "time": 7.259,
            "count": 1
        },
        {
            "time": 7.791,
            "count": 3
        },
        {
            "time": 8.193,
            "count": 1
        },
        {
            "time": 8.349,
            "count": 1
        },
        {
            "time": 8.91,
            "count": 2
        },
        {
            "time": 9.445,
            "count": 2
        },
        {
            "time": 9.981,
            "count": 2
        },
        {
            "time": 10.524,
            "count": 1
        },
        {
            "time": 11.076,
            "count": 2
        },
        {
            "time": 11.618,
            "count": 1
        },
        {
            "time": 12.164,
            "count": 2
        },
        {
            "time": 12.572,
            "count": 1
        },
        {
            "time": 12.709,
            "count": 1
        },
        {
            "time": 13.267,
            "count": 3
        },
        {
            "time": 13.827,
            "count": 1
        },
        {
            "time": 14.351,
            "count": 1
        },
        {
            "time": 14.902,
            "count": 2
        },
        {
            "time": 15.456,
            "count": 2
        },
        {
            "time": 15.982,
            "count": 2
        },
        {
            "time": 16.53,
            "count": 3
        },
        {
            "time": 16.95,
            "count": 1
        },
        {
            "time": 17.08,
            "count": 1
        },
        {
            "time": 17.632,
            "count": 3
        },
        {
            "time": 18.192,
            "count": 1
        },
        {
            "time": 18.723,
            "count": 3
        },
        {
            "time": 19.292,
            "count": 2
        },
        {
            "time": 19.824,
            "count": 2
        },
        {
            "time": 20.349,
            "count": 2
        },
        {
            "time": 20.905,
            "count": 2
        },
        {
            "time": 21.444,
            "count": 1
        },
        {
            "time": 22.047,
            "count": 1
        },
        {
            "time": 22.559,
            "count": 3
        },
        {
            "time": 23.089,
            "count": 3
        },
        {
            "time": 23.631,
            "count": 2
        },
        {
            "time": 24.201,
            "count": 2
        },
        {
            "time": 24.721,
            "count": 2
        },
        {
            "time": 25.282,
            "count": 2
        },
        {
            "time": 26.413,
            "count": 1
        },
        {
            "time": 26.911,
            "count": 2
        },
        {
            "time": 27.516,
            "count": 2
        },
        {
            "time": 27.993,
            "count": 1
        },
        {
            "time": 28.567,
            "count": 2
        },
        {
            "time": 29.1,
            "count": 2
        },
        {
            "time": 29.64,
            "count": 1
        },
        {
            "time": 30.78,
            "count": 1
        },
        {
            "time": 31.292,
            "count": 2
        },
        {
            "time": 31.883,
            "count": 1
        },
        {
            "time": 32.369,
            "count": 2
        },
        {
            "time": 32.97,
            "count": 1
        },
        {
            "time": 33.459,
            "count": 3
        },
        {
            "time": 34.556,
            "count": 3
        },
        {
            "time": 35.102,
            "count": 2
        },
        {
            "time": 35.658,
            "count": 1
        },
        {
            "time": 36.251,
            "count": 1
        },
        {
            "time": 36.74,
            "count": 2
        },
        {
            "time": 37.29,
            "count": 2
        },
        {
            "time": 37.828,
            "count": 3
        },
        {
            "time": 38.924,
            "count": 2
        },
        {
            "time": 39.515,
            "count": 2
        },
        {
            "time": 40.043,
            "count": 1
        },
        {
            "time": 40.615,
            "count": 1
        },
        {
            "time": 41.104,
            "count": 2
        },
        {
            "time": 41.668,
            "count": 1
        },
        {
            "time": 42.233,
            "count": 1
        },
        {
            "time": 43.291,
            "count": 2
        },
        {
            "time": 44.39,
            "count": 2
        },
        {
            "time": 44.928,
            "count": 2
        },
        {
            "time": 45.505,
            "count": 1
        },
        {
            "time": 46.034,
            "count": 1
        },
        {
            "time": 46.579,
            "count": 2
        },
        {
            "time": 47.154,
            "count": 1
        },
        {
            "time": 47.656,
            "count": 2
        },
        {
            "time": 48.758,
            "count": 2
        },
        {
            "time": 49.295,
            "count": 2
        },
        {
            "time": 49.858,
            "count": 2
        },
        {
            "time": 51.472,
            "count": 2
        },
        {
            "time": 52.022,
            "count": 2
        },
        {
            "time": 52.611,
            "count": 1
        },
        {
            "time": 53.122,
            "count": 3
        },
        {
            "time": 54.2,
            "count": 2
        },
        {
            "time": 54.755,
            "count": 1
        },
        {
            "time": 55.294,
            "count": 1
        },
        {
            "time": 56.425,
            "count": 1
        },
        {
            "time": 57.507,
            "count": 1
        },
        {
            "time": 58.04,
            "count": 1
        },
        {
            "time": 58.56,
            "count": 1
        },
        {
            "time": 59.123,
            "count": 2
        },
        {
            "time": 59.657,
            "count": 2
        },
        {
            "time": 60.232,
            "count": 2
        },
        {
            "time": 60.742,
            "count": 3
        },
        {
            "time": 61.345,
            "count": 1
        },
        {
            "time": 61.842,
            "count": 1
        },
        {
            "time": 62.387,
            "count": 2
        },
        {
            "time": 62.932,
            "count": 2
        },
        {
            "time": 63.497,
            "count": 1
        },
        {
            "time": 64.015,
            "count": 2
        },
        {
            "time": 64.618,
            "count": 1
        },
        {
            "time": 65.119,
            "count": 1
        },
        {
            "time": 65.71,
            "count": 1
        },
        {
            "time": 66.222,
            "count": 2
        },
        {
            "time": 66.792,
            "count": 2
        },
        {
            "time": 67.338,
            "count": 1
        },
        {
            "time": 68.394,
            "count": 1
        },
        {
            "time": 69.49,
            "count": 2
        },
        {
            "time": 70.029,
            "count": 2
        },
        {
            "time": 70.587,
            "count": 1
        },
        {
            "time": 71.179,
            "count": 1
        },
        {
            "time": 71.664,
            "count": 2
        },
        {
            "time": 73.844,
            "count": 1
        },
        {
            "time": 74.443,
            "count": 1
        },
        {
            "time": 74.993,
            "count": 1
        },
        {
            "time": 75.545,
            "count": 1
        },
        {
            "time": 76.031,
            "count": 1
        },
        {
            "time": 76.635,
            "count": 1
        },
        {
            "time": 77.121,
            "count": 3
        },
        {
            "time": 78.235,
            "count": 2
        },
        {
            "time": 78.776,
            "count": 3
        },
        {
            "time": 79.344,
            "count": 2
        },
        {
            "time": 79.877,
            "count": 1
        },
        {
            "time": 80.438,
            "count": 1
        },
        {
            "time": 81.48,
            "count": 1
        },
        {
            "time": 82.605,
            "count": 2
        },
        {
            "time": 83.161,
            "count": 3
        },
        {
            "time": 83.679,
            "count": 2
        },
        {
            "time": 84.276,
            "count": 1
        },
        {
            "time": 84.764,
            "count": 1
        },
        {
            "time": 85.321,
            "count": 3
        },
        {
            "time": 85.89,
            "count": 1
        },
        {
            "time": 86.449,
            "count": 1
        },
        {
            "time": 88.045,
            "count": 2
        },
        {
            "time": 88.604,
            "count": 2
        },
        {
            "time": 89.133,
            "count": 2
        },
        {
            "time": 89.693,
            "count": 2
        },
        {
            "time": 91.334,
            "count": 2
        },
        {
            "time": 91.909,
            "count": 1
        },
        {
            "time": 92.422,
            "count": 3
        },
        {
            "time": 92.97,
            "count": 2
        },
        {
            "time": 93.516,
            "count": 1
        },
        {
            "time": 94.59,
            "count": 2
        },
        {
            "time": 95.132,
            "count": 1
        },
        {
            "time": 95.682,
            "count": 2
        },
        {
            "time": 96.802,
            "count": 1
        },
        {
            "time": 97.326,
            "count": 3
        },
        {
            "time": 97.862,
            "count": 1
        },
        {
            "time": 98.945,
            "count": 2
        },
        {
            "time": 100.086,
            "count": 1
        },
        {
            "time": 100.625,
            "count": 2
        },
        {
            "time": 101.184,
            "count": 1
        },
        {
            "time": 101.696,
            "count": 3
        },
        {
            "time": 102.223,
            "count": 1
        },
        {
            "time": 102.778,
            "count": 3
        },
        {
            "time": 103.308,
            "count": 1
        },
        {
            "time": 103.909,
            "count": 1
        },
        {
            "time": 104.404,
            "count": 1
        },
        {
            "time": 104.953,
            "count": 3
        },
        {
            "time": 105.51,
            "count": 1
        },
        {
            "time": 106.1,
            "count": 1
        },
        {
            "time": 106.588,
            "count": 1
        },
        {
            "time": 107.152,
            "count": 2
        },
        {
            "time": 107.677,
            "count": 1
        },
        {
            "time": 108.775,
            "count": 2
        },
        {
            "time": 109.367,
            "count": 1
        },
        {
            "time": 109.87,
            "count": 1
        },
        {
            "time": 110.416,
            "count": 1
        },
        {
            "time": 110.956,
            "count": 3
        },
        {
            "time": 111.519,
            "count": 2
        },
        {
            "time": 111.844,
            "count": 2
        },
        {
            "time": 111.996,
            "count": 3
        },
        {
            "time": 112.489,
            "count": 1
        },
        {
            "time": 112.591,
            "count": 1
        },
        {
            "time": 113.145,
            "count": 1
        },
        {
            "time": 113.737,
            "count": 1
        },
        {
            "time": 114.244,
            "count": 1
        },
        {
            "time": 116.416,
            "count": 2
        },
        {
            "time": 117.548,
            "count": 1
        },
        {
            "time": 118.612,
            "count": 2
        },
        {
            "time": 119.692,
            "count": 3
        },
        {
            "time": 120.782,
            "count": 3
        },
        {
            "time": 121.913,
            "count": 1
        },
        {
            "time": 122.471,
            "count": 1
        },
        {
            "time": 122.978,
            "count": 1
        },
        {
            "time": 124.057,
            "count": 2
        },
        {
            "time": 125.151,
            "count": 3
        },
        {
            "time": 126.245,
            "count": 3
        },
        {
            "time": 127.347,
            "count": 1
        },
        {
            "time": 128.424,
            "count": 2
        },
        {
            "time": 129.516,
            "count": 3
        },
        {
            "time": 130.614,
            "count": 3
        },
        {
            "time": 131.203,
            "count": 1
        },
        {
            "time": 131.713,
            "count": 3
        },
        {
            "time": 132.792,
            "count": 3
        },
        {
            "time": 133.881,
            "count": 1
        },
        {
            "time": 134.98,
            "count": 2
        },
        {
            "time": 136.08,
            "count": 2
        },
        {
            "time": 137.158,
            "count": 3
        },
        {
            "time": 138.284,
            "count": 1
        },
        {
            "time": 139.346,
            "count": 2
        },
        {
            "time": 139.974,
            "count": 1
        },
        {
            "time": 149.215,
            "count": 1
        },
        {
            "time": 149.768,
            "count": 1
        },
        {
            "time": 150.276,
            "count": 3
        },
        {
            "time": 151.347,
            "count": 2
        },
        {
            "time": 151.894,
            "count": 1
        },
        {
            "time": 152.442,
            "count": 1
        },
        {
            "time": 153.034,
            "count": 1
        },
        {
            "time": 153.533,
            "count": 2
        },
        {
            "time": 154.095,
            "count": 3
        },
        {
            "time": 154.623,
            "count": 1
        },
        {
            "time": 155.712,
            "count": 3
        },
        {
            "time": 156.249,
            "count": 3
        },
        {
            "time": 156.808,
            "count": 1
        },
        {
            "time": 157.403,
            "count": 1
        },
        {
            "time": 157.931,
            "count": 2
        },
        {
            "time": 158.444,
            "count": 2
        },
        {
            "time": 159.028,
            "count": 1
        },
        {
            "time": 159.592,
            "count": 1
        },
        {
            "time": 160.082,
            "count": 3
        },
        {
            "time": 160.673,
            "count": 1
        },
        {
            "time": 161.176,
            "count": 1
        },
        {
            "time": 161.731,
            "count": 3
        },
        {
            "time": 162.273,
            "count": 2
        },
        {
            "time": 162.869,
            "count": 1
        },
        {
            "time": 163.378,
            "count": 1
        },
        {
            "time": 164.445,
            "count": 3
        },
        {
            "time": 165.584,
            "count": 1
        },
        {
            "time": 166.133,
            "count": 1
        },
        {
            "time": 166.643,
            "count": 2
        },
        {
            "time": 167.237,
            "count": 1
        },
        {
            "time": 167.723,
            "count": 2
        },
        {
            "time": 168.275,
            "count": 2
        },
        {
            "time": 168.852,
            "count": 1
        },
        {
            "time": 169.95,
            "count": 1
        },
        {
            "time": 170.45,
            "count": 2
        },
        {
            "time": 171.03,
            "count": 1
        },
        {
            "time": 171.601,
            "count": 1
        },
        {
            "time": 172.126,
            "count": 1
        },
        {
            "time": 172.657,
            "count": 3
        },
        {
            "time": 173.216,
            "count": 1
        },
        {
            "time": 174.293,
            "count": 2
        },
        {
            "time": 174.809,
            "count": 1
        },
        {
            "time": 174.929,
            "count": 1
        },
        {
            "time": 175.376,
            "count": 2
        },
        {
            "time": 175.907,
            "count": 2
        },
        {
            "time": 176.446,
            "count": 3
        },
        {
            "time": 177.545,
            "count": 2
        },
        {
            "time": 179.74,
            "count": 1
        },
        {
            "time": 180.335,
            "count": 1
        },
        {
            "time": 180.811,
            "count": 2
        },
        {
            "time": 181.385,
            "count": 1
        },
        {
            "time": 181.914,
            "count": 2
        },
        {
            "time": 184.126,
            "count": 1
        },
        {
            "time": 184.66,
            "count": 2
        },
        {
            "time": 185.229,
            "count": 1
        },
        {
            "time": 187.372,
            "count": 2
        },
        {
            "time": 188.476,
            "count": 2
        },
        {
            "time": 190.121,
            "count": 3
        },
        {
            "time": 190.684,
            "count": 1
        },
        {
            "time": 191.745,
            "count": 3
        },
        {
            "time": 192.843,
            "count": 2
        },
        {
            "time": 193.397,
            "count": 1
        },
        {
            "time": 193.914,
            "count": 1
        },
        {
            "time": 194.486,
            "count": 3
        },
        {
            "time": 195.013,
            "count": 2
        },
        {
            "time": 195.556,
            "count": 2
        },
        {
            "time": 196.109,
            "count": 1
        },
        {
            "time": 196.702,
            "count": 1
        },
        {
            "time": 197.205,
            "count": 1
        },
        {
            "time": 197.736,
            "count": 2
        },
        {
            "time": 198.293,
            "count": 3
        },
        {
            "time": 198.854,
            "count": 2
        },
        {
            "time": 199.378,
            "count": 2
        },
        {
            "time": 199.949,
            "count": 2
        },
        {
            "time": 200.466,
            "count": 3
        },
        {
            "time": 201.579,
            "count": 3
        },
        {
            "time": 202.17,
            "count": 1
        },
        {
            "time": 202.653,
            "count": 2
        },
        {
            "time": 203.224,
            "count": 3
        },
        {
            "time": 203.765,
            "count": 2
        },
        {
            "time": 204.837,
            "count": 2
        },
        {
            "time": 205.432,
            "count": 1
        },
        {
            "time": 205.944,
            "count": 1
        },
        {
            "time": 207.019,
            "count": 2
        },
        {
            "time": 208.116,
            "count": 1
        },
        {
            "time": 209.212,
            "count": 3
        },
        {
            "time": 209.783,
            "count": 3
        },
        {
            "time": 210.305,
            "count": 1
        }
    ],
    "melody": [
        {
            "time": 0.397641723,
            "count": 1,
            "index": 2
        },
        {
            "time": 0.65015873,
            "count": 1,
            "index": 2
        },
        {
            "time": 1.216145125,
            "count": 1,
            "index": 2
        },
        {
            "time": 2.716734694,
            "count": 1,
            "index": 1
        },
        {
            "time": 3.111473923,
            "count": 1,
            "index": 3
        },
        {
            "time": 3.36399093,
            "count": 1,
            "index": 2
        },
        {
            "time": 3.793560091,
            "count": 1,
            "index": 2
        },
        {
            "time": 4.757188209,
            "count": 1,
            "index": 2
        },
        {
            "time": 5.009705215,
            "count": 1,
            "index": 1
        },
        {
            "time": 7.671292517,
            "count": 1,
            "index": 1
        },
        {
            "time": 7.923809524,
            "count": 1,
            "index": 2
        },
        {
            "time": 8.176326531,
            "count": 1,
            "index": 3
        },
        {
            "time": 9.459229025,
            "count": 1,
            "index": 3
        },
        {
            "time": 9.975873016,
            "count": 1,
            "index": 3
        },
        {
            "time": 10.463492063,
            "count": 1,
            "index": 2
        },
        {
            "time": 10.71600907,
            "count": 1,
            "index": 2
        },
        {
            "time": 11.810249433,
            "count": 1,
            "index": 2
        },
        {
            "time": 12.06276644,
            "count": 1,
            "index": 3
        },
        {
            "time": 12.379138322,
            "count": 1,
            "index": 2
        },
        {
            "time": 12.631655329,
            "count": 1,
            "index": 2
        },
        {
            "time": 13.766530612,
            "count": 1,
            "index": 3
        },
        {
            "time": 14.410884354,
            "count": 1,
            "index": 2
        },
        {
            "time": 14.840453515,
            "count": 1,
            "index": 2
        },
        {
            "time": 15.092970522,
            "count": 1,
            "index": 3
        },
        {
            "time": 16.222040816,
            "count": 1,
            "index": 3
        },
        {
            "time": 16.474557823,
            "count": 1,
            "index": 2
        },
        {
            "time": 16.7938322,
            "count": 1,
            "index": 3
        },
        {
            "time": 17.046349206,
            "count": 1,
            "index": 3
        },
        {
            "time": 18.143492063,
            "count": 1,
            "index": 4
        },
        {
            "time": 19.255147392,
            "count": 1,
            "index": 3
        },
        {
            "time": 19.646984127,
            "count": 1,
            "index": 3
        },
        {
            "time": 20.276825397,
            "count": 1,
            "index": 3
        },
        {
            "time": 20.529342404,
            "count": 1,
            "index": 2
        },
        {
            "time": 20.78185941,
            "count": 1,
            "index": 1
        },
        {
            "time": 21.034376417,
            "count": 1,
            "index": 3
        },
        {
            "time": 21.286893424,
            "count": 1,
            "index": 1
        },
        {
            "time": 21.539410431,
            "count": 1,
            "index": 2
        },
        {
            "time": 21.791927438,
            "count": 1,
            "index": 2
        },
        {
            "time": 22.044444444,
            "count": 1,
            "index": 1
        },
        {
            "time": 22.296961451,
            "count": 1,
            "index": 4
        },
        {
            "time": 22.549478458,
            "count": 1,
            "index": 2
        },
        {
            "time": 22.801995465,
            "count": 1,
            "index": 1
        },
        {
            "time": 23.054512472,
            "count": 1,
            "index": 3
        },
        {
            "time": 23.434739229,
            "count": 1,
            "index": 5
        },
        {
            "time": 23.687256236,
            "count": 1,
            "index": 5
        },
        {
            "time": 24.662494331,
            "count": 1,
            "index": 3
        },
        {
            "time": 24.993378685,
            "count": 1,
            "index": 3
        },
        {
            "time": 25.245895692,
            "count": 1,
            "index": 1
        },
        {
            "time": 25.498412698,
            "count": 1,
            "index": 3
        },
        {
            "time": 25.750929705,
            "count": 1,
            "index": 1
        },
        {
            "time": 26.853877551,
            "count": 1,
            "index": 2
        },
        {
            "time": 27.106394558,
            "count": 1,
            "index": 3
        },
        {
            "time": 27.962630385,
            "count": 1,
            "index": 5
        },
        {
            "time": 28.351564626,
            "count": 1,
            "index": 1
        },
        {
            "time": 29.109115646,
            "count": 1,
            "index": 5
        },
        {
            "time": 29.361632653,
            "count": 1,
            "index": 1
        },
        {
            "time": 29.61414966,
            "count": 1,
            "index": 3
        },
        {
            "time": 29.994376417,
            "count": 1,
            "index": 1
        },
        {
            "time": 30.963809524,
            "count": 1,
            "index": 2
        },
        {
            "time": 31.239546485,
            "count": 1,
            "index": 4
        },
        {
            "time": 31.512380952,
            "count": 1,
            "index": 4
        },
        {
            "time": 31.921632653,
            "count": 1,
            "index": 1
        },
        {
            "time": 32.17414966,
            "count": 1,
            "index": 1
        },
        {
            "time": 32.426666667,
            "count": 1,
            "index": 4
        },
        {
            "time": 32.708208617,
            "count": 1,
            "index": 1
        },
        {
            "time": 32.960725624,
            "count": 1,
            "index": 5
        },
        {
            "time": 33.21324263,
            "count": 1,
            "index": 3
        },
        {
            "time": 33.465759637,
            "count": 1,
            "index": 2
        },
        {
            "time": 33.718276644,
            "count": 1,
            "index": 1
        },
        {
            "time": 33.970793651,
            "count": 1,
            "index": 2
        },
        {
            "time": 34.342312925,
            "count": 1,
            "index": 1
        },
        {
            "time": 35.610702948,
            "count": 1,
            "index": 3
        },
        {
            "time": 35.863219955,
            "count": 1,
            "index": 1
        },
        {
            "time": 36.115736961,
            "count": 1,
            "index": 4
        },
        {
            "time": 36.368253968,
            "count": 1,
            "index": 1
        },
        {
            "time": 36.826848073,
            "count": 1,
            "index": 2
        },
        {
            "time": 37.079365079,
            "count": 1,
            "index": 1
        },
        {
            "time": 37.331882086,
            "count": 1,
            "index": 4
        },
        {
            "time": 37.584399093,
            "count": 1,
            "index": 4
        },
        {
            "time": 37.8369161,
            "count": 1,
            "index": 5
        },
        {
            "time": 38.089433107,
            "count": 1,
            "index": 5
        },
        {
            "time": 38.341950113,
            "count": 1,
            "index": 2
        },
        {
            "time": 38.59446712,
            "count": 1,
            "index": 5
        },
        {
            "time": 38.846984127,
            "count": 1,
            "index": 3
        },
        {
            "time": 39.099501134,
            "count": 1,
            "index": 2
        },
        {
            "time": 39.352018141,
            "count": 1,
            "index": 2
        },
        {
            "time": 39.604535147,
            "count": 1,
            "index": 4
        },
        {
            "time": 42.115192744,
            "count": 1,
            "index": 3
        },
        {
            "time": 42.367709751,
            "count": 1,
            "index": 1
        },
        {
            "time": 42.620226757,
            "count": 1,
            "index": 3
        },
        {
            "time": 42.945306122,
            "count": 1,
            "index": 3
        },
        {
            "time": 43.197823129,
            "count": 1,
            "index": 3
        },
        {
            "time": 45.389206349,
            "count": 1,
            "index": 3
        },
        {
            "time": 46.53569161,
            "count": 1,
            "index": 2
        },
        {
            "time": 46.788208617,
            "count": 1,
            "index": 2
        },
        {
            "time": 47.040725624,
            "count": 1,
            "index": 2
        },
        {
            "time": 47.301950113,
            "count": 1,
            "index": 3
        },
        {
            "time": 47.55446712,
            "count": 1,
            "index": 1
        },
        {
            "time": 48.329433107,
            "count": 1,
            "index": 1
        },
        {
            "time": 48.581950113,
            "count": 1,
            "index": 4
        },
        {
            "time": 48.83446712,
            "count": 1,
            "index": 5
        },
        {
            "time": 49.086984127,
            "count": 1,
            "index": 3
        },
        {
            "time": 49.339501134,
            "count": 1,
            "index": 1
        },
        {
            "time": 49.592018141,
            "count": 1,
            "index": 3
        },
        {
            "time": 49.844535147,
            "count": 1,
            "index": 5
        },
        {
            "time": 50.097052154,
            "count": 1,
            "index": 4
        },
        {
            "time": 50.901043084,
            "count": 1,
            "index": 5
        },
        {
            "time": 51.153560091,
            "count": 1,
            "index": 1
        },
        {
            "time": 51.475736961,
            "count": 1,
            "index": 2
        },
        {
            "time": 51.821133787,
            "count": 1,
            "index": 3
        },
        {
            "time": 52.073650794,
            "count": 1,
            "index": 5
        },
        {
            "time": 53.048888889,
            "count": 1,
            "index": 4
        },
        {
            "time": 53.725170068,
            "count": 1,
            "index": 3
        },
        {
            "time": 53.977687075,
            "count": 1,
            "index": 2
        },
        {
            "time": 54.230204082,
            "count": 1,
            "index": 2
        },
        {
            "time": 54.482721088,
            "count": 1,
            "index": 4
        },
        {
            "time": 54.735238095,
            "count": 1,
            "index": 4
        },
        {
            "time": 55.275102041,
            "count": 1,
            "index": 5
        },
        {
            "time": 55.527619048,
            "count": 1,
            "index": 5
        },
        {
            "time": 56.154557823,
            "count": 1,
            "index": 5
        },
        {
            "time": 56.40707483,
            "count": 1,
            "index": 5
        },
        {
            "time": 56.659591837,
            "count": 1,
            "index": 4
        },
        {
            "time": 56.912108844,
            "count": 1,
            "index": 1
        },
        {
            "time": 57.173333333,
            "count": 1,
            "index": 2
        },
        {
            "time": 57.42585034,
            "count": 1,
            "index": 3
        },
        {
            "time": 60.157097506,
            "count": 1,
            "index": 3
        },
        {
            "time": 60.537324263,
            "count": 1,
            "index": 2
        },
        {
            "time": 61.791201814,
            "count": 1,
            "index": 3
        },
        {
            "time": 62.319455782,
            "count": 1,
            "index": 2
        },
        {
            "time": 62.571972789,
            "count": 1,
            "index": 2
        },
        {
            "time": 65.131972789,
            "count": 1,
            "index": 1
        },
        {
            "time": 65.384489796,
            "count": 1,
            "index": 1
        },
        {
            "time": 65.637006803,
            "count": 1,
            "index": 1
        },
        {
            "time": 65.88952381,
            "count": 1,
            "index": 1
        },
        {
            "time": 66.142040816,
            "count": 1,
            "index": 5
        },
        {
            "time": 66.394557823,
            "count": 1,
            "index": 4
        },
        {
            "time": 66.64707483,
            "count": 1,
            "index": 1
        },
        {
            "time": 66.899591837,
            "count": 1,
            "index": 5
        },
        {
            "time": 67.152108844,
            "count": 1,
            "index": 2
        },
        {
            "time": 67.40462585,
            "count": 1,
            "index": 5
        },
        {
            "time": 67.657142857,
            "count": 1,
            "index": 3
        },
        {
            "time": 67.909659864,
            "count": 1,
            "index": 3
        },
        {
            "time": 68.162176871,
            "count": 1,
            "index": 1
        },
        {
            "time": 68.414693878,
            "count": 1,
            "index": 2
        },
        {
            "time": 68.667210884,
            "count": 1,
            "index": 4
        },
        {
            "time": 68.919727891,
            "count": 1,
            "index": 5
        },
        {
            "time": 69.172244898,
            "count": 1,
            "index": 3
        },
        {
            "time": 69.424761905,
            "count": 1,
            "index": 1
        },
        {
            "time": 69.703401361,
            "count": 1,
            "index": 3
        },
        {
            "time": 69.955918367,
            "count": 1,
            "index": 2
        },
        {
            "time": 70.208435374,
            "count": 1,
            "index": 4
        },
        {
            "time": 70.539319728,
            "count": 1,
            "index": 3
        },
        {
            "time": 70.791836735,
            "count": 1,
            "index": 5
        },
        {
            "time": 71.044353741,
            "count": 1,
            "index": 1
        },
        {
            "time": 71.296870748,
            "count": 1,
            "index": 2
        },
        {
            "time": 71.549387755,
            "count": 1,
            "index": 5
        },
        {
            "time": 71.801904762,
            "count": 1,
            "index": 1
        },
        {
            "time": 72.054421769,
            "count": 1,
            "index": 2
        },
        {
            "time": 72.306938776,
            "count": 1,
            "index": 1
        },
        {
            "time": 72.707482993,
            "count": 1,
            "index": 2
        },
        {
            "time": 72.96,
            "count": 1,
            "index": 4
        },
        {
            "time": 73.212517007,
            "count": 1,
            "index": 2
        },
        {
            "time": 73.465034014,
            "count": 1,
            "index": 2
        },
        {
            "time": 73.71755102,
            "count": 1,
            "index": 1
        },
        {
            "time": 73.970068027,
            "count": 1,
            "index": 1
        },
        {
            "time": 74.353197279,
            "count": 1,
            "index": 3
        },
        {
            "time": 74.605714286,
            "count": 1,
            "index": 3
        },
        {
            "time": 74.858231293,
            "count": 1,
            "index": 4
        },
        {
            "time": 75.110748299,
            "count": 1,
            "index": 5
        },
        {
            "time": 75.363265306,
            "count": 1,
            "index": 2
        },
        {
            "time": 75.615782313,
            "count": 1,
            "index": 2
        },
        {
            "time": 75.86829932,
            "count": 1,
            "index": 3
        },
        {
            "time": 76.120816327,
            "count": 1,
            "index": 1
        },
        {
            "time": 76.384943311,
            "count": 1,
            "index": 3
        },
        {
            "time": 76.637460317,
            "count": 1,
            "index": 1
        },
        {
            "time": 76.889977324,
            "count": 1,
            "index": 4
        },
        {
            "time": 77.142494331,
            "count": 1,
            "index": 3
        },
        {
            "time": 77.395011338,
            "count": 1,
            "index": 3
        },
        {
            "time": 77.647528345,
            "count": 1,
            "index": 3
        },
        {
            "time": 77.900045351,
            "count": 1,
            "index": 2
        },
        {
            "time": 78.152562358,
            "count": 1,
            "index": 5
        },
        {
            "time": 79.014603175,
            "count": 1,
            "index": 2
        },
        {
            "time": 79.267120181,
            "count": 1,
            "index": 5
        },
        {
            "time": 79.519637188,
            "count": 1,
            "index": 4
        },
        {
            "time": 79.772154195,
            "count": 1,
            "index": 5
        },
        {
            "time": 80.024671202,
            "count": 1,
            "index": 2
        },
        {
            "time": 80.277188209,
            "count": 1,
            "index": 2
        },
        {
            "time": 80.625487528,
            "count": 1,
            "index": 2
        },
        {
            "time": 80.878004535,
            "count": 1,
            "index": 5
        },
        {
            "time": 81.130521542,
            "count": 1,
            "index": 4
        },
        {
            "time": 81.499138322,
            "count": 1,
            "index": 5
        },
        {
            "time": 81.751655329,
            "count": 1,
            "index": 3
        },
        {
            "time": 82.004172336,
            "count": 1,
            "index": 4
        },
        {
            "time": 82.256689342,
            "count": 1,
            "index": 3
        },
        {
            "time": 82.509206349,
            "count": 1,
            "index": 4
        },
        {
            "time": 82.761723356,
            "count": 1,
            "index": 1
        },
        {
            "time": 83.014240363,
            "count": 1,
            "index": 5
        },
        {
            "time": 83.26675737,
            "count": 1,
            "index": 1
        },
        {
            "time": 83.519274376,
            "count": 1,
            "index": 2
        },
        {
            "time": 84.160725624,
            "count": 1,
            "index": 5
        },
        {
            "time": 85.829659864,
            "count": 1,
            "index": 5
        },
        {
            "time": 86.082176871,
            "count": 1,
            "index": 2
        },
        {
            "time": 86.334693878,
            "count": 1,
            "index": 2
        },
        {
            "time": 86.587210884,
            "count": 1,
            "index": 1
        },
        {
            "time": 86.839727891,
            "count": 1,
            "index": 2
        },
        {
            "time": 87.092244898,
            "count": 1,
            "index": 5
        },
        {
            "time": 87.344761905,
            "count": 1,
            "index": 2
        },
        {
            "time": 87.597278912,
            "count": 1,
            "index": 5
        },
        {
            "time": 90.157278912,
            "count": 1,
            "index": 1
        },
        {
            "time": 90.409795918,
            "count": 1,
            "index": 2
        },
        {
            "time": 90.694240363,
            "count": 1,
            "index": 1
        },
        {
            "time": 91.109297052,
            "count": 1,
            "index": 5
        },
        {
            "time": 91.408253968,
            "count": 1,
            "index": 2
        },
        {
            "time": 91.79138322,
            "count": 1,
            "index": 5
        },
        {
            "time": 92.043900227,
            "count": 1,
            "index": 4
        },
        {
            "time": 92.296417234,
            "count": 1,
            "index": 4
        },
        {
            "time": 92.54893424,
            "count": 1,
            "index": 4
        },
        {
            "time": 92.888526077,
            "count": 1,
            "index": 5
        },
        {
            "time": 93.141043084,
            "count": 1,
            "index": 2
        },
        {
            "time": 93.393560091,
            "count": 1,
            "index": 1
        },
        {
            "time": 93.646077098,
            "count": 1,
            "index": 5
        },
        {
            "time": 93.979863946,
            "count": 1,
            "index": 3
        },
        {
            "time": 94.232380952,
            "count": 1,
            "index": 5
        },
        {
            "time": 94.531337868,
            "count": 1,
            "index": 2
        },
        {
            "time": 94.783854875,
            "count": 1,
            "index": 1
        },
        {
            "time": 95.050884354,
            "count": 1,
            "index": 4
        },
        {
            "time": 95.303401361,
            "count": 1,
            "index": 3
        },
        {
            "time": 95.555918367,
            "count": 1,
            "index": 3
        },
        {
            "time": 95.808435374,
            "count": 1,
            "index": 4
        },
        {
            "time": 96.060952381,
            "count": 1,
            "index": 4
        },
        {
            "time": 96.313469388,
            "count": 1,
            "index": 4
        },
        {
            "time": 96.673378685,
            "count": 1,
            "index": 3
        },
        {
            "time": 97.573151927,
            "count": 1,
            "index": 5
        },
        {
            "time": 97.825668934,
            "count": 1,
            "index": 4
        },
        {
            "time": 98.324897959,
            "count": 1,
            "index": 2
        },
        {
            "time": 98.577414966,
            "count": 1,
            "index": 3
        },
        {
            "time": 98.864761905,
            "count": 1,
            "index": 4
        },
        {
            "time": 99.117278912,
            "count": 1,
            "index": 4
        },
        {
            "time": 99.424943311,
            "count": 1,
            "index": 2
        },
        {
            "time": 99.816780045,
            "count": 1,
            "index": 5
        },
        {
            "time": 100.069297052,
            "count": 1,
            "index": 5
        },
        {
            "time": 100.321814059,
            "count": 1,
            "index": 5
        },
        {
            "time": 100.574331066,
            "count": 1,
            "index": 1
        },
        {
            "time": 100.826848073,
            "count": 1,
            "index": 2
        },
        {
            "time": 101.079365079,
            "count": 1,
            "index": 2
        },
        {
            "time": 105.186394558,
            "count": 1,
            "index": 3
        },
        {
            "time": 106.019410431,
            "count": 1,
            "index": 3
        },
        {
            "time": 107.096235828,
            "count": 1,
            "index": 4
        },
        {
            "time": 108.161451247,
            "count": 1,
            "index": 3
        },
        {
            "time": 109.264399093,
            "count": 1,
            "index": 2
        },
        {
            "time": 112.547120181,
            "count": 1,
            "index": 1
        },
        {
            "time": 113.342403628,
            "count": 1,
            "index": 3
        },
        {
            "time": 113.594920635,
            "count": 1,
            "index": 5
        },
        {
            "time": 113.847437642,
            "count": 1,
            "index": 2
        },
        {
            "time": 114.732698413,
            "count": 1,
            "index": 2
        },
        {
            "time": 114.98521542,
            "count": 1,
            "index": 5
        },
        {
            "time": 115.237732426,
            "count": 1,
            "index": 3
        },
        {
            "time": 115.490249433,
            "count": 1,
            "index": 3
        },
        {
            "time": 115.806621315,
            "count": 1,
            "index": 5
        },
        {
            "time": 116.070748299,
            "count": 1,
            "index": 1
        },
        {
            "time": 116.323265306,
            "count": 1,
            "index": 3
        },
        {
            "time": 116.886349206,
            "count": 1,
            "index": 4
        },
        {
            "time": 117.707755102,
            "count": 1,
            "index": 4
        },
        {
            "time": 117.986394558,
            "count": 1,
            "index": 3
        },
        {
            "time": 118.238911565,
            "count": 1,
            "index": 4
        },
        {
            "time": 118.491428571,
            "count": 1,
            "index": 1
        },
        {
            "time": 118.743945578,
            "count": 1,
            "index": 5
        },
        {
            "time": 119.080634921,
            "count": 1,
            "index": 5
        },
        {
            "time": 120.01814059,
            "count": 1,
            "index": 1
        },
        {
            "time": 120.270657596,
            "count": 1,
            "index": 4
        },
        {
            "time": 120.523174603,
            "count": 1,
            "index": 1
        },
        {
            "time": 120.836643991,
            "count": 1,
            "index": 4
        },
        {
            "time": 121.182040816,
            "count": 1,
            "index": 1
        },
        {
            "time": 121.434557823,
            "count": 1,
            "index": 3
        },
        {
            "time": 122.029569161,
            "count": 1,
            "index": 1
        },
        {
            "time": 122.282086168,
            "count": 1,
            "index": 3
        },
        {
            "time": 122.534603175,
            "count": 1,
            "index": 4
        },
        {
            "time": 123.483718821,
            "count": 1,
            "index": 1
        },
        {
            "time": 124.563446712,
            "count": 1,
            "index": 5
        },
        {
            "time": 125.61414966,
            "count": 1,
            "index": 5
        },
        {
            "time": 126.484897959,
            "count": 1,
            "index": 3
        },
        {
            "time": 126.737414966,
            "count": 1,
            "index": 5
        },
        {
            "time": 130.002721088,
            "count": 1,
            "index": 1
        },
        {
            "time": 130.255238095,
            "count": 1,
            "index": 1
        },
        {
            "time": 130.893786848,
            "count": 1,
            "index": 1
        },
        {
            "time": 131.146303855,
            "count": 1,
            "index": 1
        },
        {
            "time": 131.398820862,
            "count": 1,
            "index": 1
        },
        {
            "time": 131.651337868,
            "count": 1,
            "index": 1
        },
        {
            "time": 131.903854875,
            "count": 1,
            "index": 2
        },
        {
            "time": 132.156371882,
            "count": 1,
            "index": 4
        },
        {
            "time": 132.408888889,
            "count": 1,
            "index": 1
        },
        {
            "time": 132.661405896,
            "count": 1,
            "index": 2
        },
        {
            "time": 132.913922902,
            "count": 1,
            "index": 2
        },
        {
            "time": 133.166439909,
            "count": 1,
            "index": 4
        },
        {
            "time": 133.418956916,
            "count": 1,
            "index": 1
        },
        {
            "time": 134.321632653,
            "count": 1,
            "index": 1
        },
        {
            "time": 134.57414966,
            "count": 1,
            "index": 5
        },
        {
            "time": 134.997913832,
            "count": 1,
            "index": 2
        },
        {
            "time": 135.250430839,
            "count": 1,
            "index": 3
        },
        {
            "time": 135.502947846,
            "count": 1,
            "index": 3
        },
        {
            "time": 136.544943311,
            "count": 1,
            "index": 5
        },
        {
            "time": 137.334421769,
            "count": 1,
            "index": 1
        },
        {
            "time": 137.586938776,
            "count": 1,
            "index": 5
        },
        {
            "time": 137.839455782,
            "count": 1,
            "index": 4
        },
        {
            "time": 138.768253968,
            "count": 1,
            "index": 2
        },
        {
            "time": 139.281995465,
            "count": 1,
            "index": 4
        },
        {
            "time": 139.534512472,
            "count": 1,
            "index": 2
        },
        {
            "time": 140.274648526,
            "count": 1,
            "index": 1
        },
        {
            "time": 140.527165533,
            "count": 1,
            "index": 5
        },
        {
            "time": 140.77968254,
            "count": 1,
            "index": 2
        },
        {
            "time": 141.032199546,
            "count": 1,
            "index": 2
        },
        {
            "time": 141.307936508,
            "count": 1,
            "index": 1
        },
        {
            "time": 141.998730159,
            "count": 1,
            "index": 1
        },
        {
            "time": 142.46893424,
            "count": 1,
            "index": 2
        },
        {
            "time": 142.721451247,
            "count": 1,
            "index": 4
        },
        {
            "time": 143.084263039,
            "count": 1,
            "index": 5
        },
        {
            "time": 143.458684807,
            "count": 1,
            "index": 1
        },
        {
            "time": 143.79537415,
            "count": 1,
            "index": 3
        },
        {
            "time": 144.047891156,
            "count": 1,
            "index": 1
        },
        {
            "time": 144.300408163,
            "count": 1,
            "index": 3
        },
        {
            "time": 144.637097506,
            "count": 1,
            "index": 1
        },
        {
            "time": 144.889614512,
            "count": 1,
            "index": 5
        },
        {
            "time": 145.258231293,
            "count": 1,
            "index": 1
        },
        {
            "time": 145.652970522,
            "count": 1,
            "index": 5
        },
        {
            "time": 145.928707483,
            "count": 1,
            "index": 2
        },
        {
            "time": 146.294421769,
            "count": 1,
            "index": 1
        },
        {
            "time": 146.854603175,
            "count": 1,
            "index": 2
        },
        {
            "time": 147.107120181,
            "count": 1,
            "index": 5
        },
        {
            "time": 147.487346939,
            "count": 1,
            "index": 5
        },
        {
            "time": 147.87047619,
            "count": 1,
            "index": 3
        },
        {
            "time": 148.201360544,
            "count": 1,
            "index": 3
        },
        {
            "time": 148.535147392,
            "count": 1,
            "index": 1
        },
        {
            "time": 148.787664399,
            "count": 1,
            "index": 2
        },
        {
            "time": 149.040181406,
            "count": 1,
            "index": 3
        },
        {
            "time": 149.292698413,
            "count": 1,
            "index": 1
        },
        {
            "time": 149.54521542,
            "count": 1,
            "index": 5
        },
        {
            "time": 149.797732426,
            "count": 1,
            "index": 2
        },
        {
            "time": 150.050249433,
            "count": 1,
            "index": 1
        },
        {
            "time": 150.30276644,
            "count": 1,
            "index": 5
        },
        {
            "time": 150.555283447,
            "count": 1,
            "index": 1
        },
        {
            "time": 150.967437642,
            "count": 1,
            "index": 2
        },
        {
            "time": 151.243174603,
            "count": 1,
            "index": 2
        },
        {
            "time": 151.579863946,
            "count": 1,
            "index": 4
        },
        {
            "time": 151.832380952,
            "count": 1,
            "index": 3
        },
        {
            "time": 152.221315193,
            "count": 1,
            "index": 3
        },
        {
            "time": 154.810340136,
            "count": 1,
            "index": 3
        },
        {
            "time": 155.062857143,
            "count": 1,
            "index": 2
        },
        {
            "time": 155.776870748,
            "count": 1,
            "index": 3
        },
        {
            "time": 156.029387755,
            "count": 1,
            "index": 1
        },
        {
            "time": 156.281904762,
            "count": 1,
            "index": 2
        },
        {
            "time": 156.534421769,
            "count": 1,
            "index": 3
        },
        {
            "time": 156.786938776,
            "count": 1,
            "index": 2
        },
        {
            "time": 157.039455782,
            "count": 1,
            "index": 2
        },
        {
            "time": 157.291972789,
            "count": 1,
            "index": 1
        },
        {
            "time": 157.544489796,
            "count": 1,
            "index": 2
        },
        {
            "time": 157.797006803,
            "count": 1,
            "index": 5
        },
        {
            "time": 158.04952381,
            "count": 1,
            "index": 1
        },
        {
            "time": 158.302040816,
            "count": 1,
            "index": 5
        },
        {
            "time": 158.844807256,
            "count": 1,
            "index": 1
        },
        {
            "time": 159.097324263,
            "count": 1,
            "index": 2
        },
        {
            "time": 159.518185941,
            "count": 1,
            "index": 3
        },
        {
            "time": 159.770702948,
            "count": 1,
            "index": 5
        },
        {
            "time": 160.023219955,
            "count": 1,
            "index": 5
        },
        {
            "time": 160.275736961,
            "count": 1,
            "index": 5
        },
        {
            "time": 160.621133787,
            "count": 1,
            "index": 5
        },
        {
            "time": 160.873650794,
            "count": 1,
            "index": 1
        },
        {
            "time": 161.1261678,
            "count": 1,
            "index": 4
        },
        {
            "time": 161.378684807,
            "count": 1,
            "index": 4
        },
        {
            "time": 161.631201814,
            "count": 1,
            "index": 2
        },
        {
            "time": 162.205895692,
            "count": 1,
            "index": 4
        },
        {
            "time": 162.458412698,
            "count": 1,
            "index": 5
        },
        {
            "time": 162.710929705,
            "count": 1,
            "index": 1
        },
        {
            "time": 162.963446712,
            "count": 1,
            "index": 4
        },
        {
            "time": 163.262403628,
            "count": 1,
            "index": 3
        },
        {
            "time": 163.514920635,
            "count": 1,
            "index": 3
        },
        {
            "time": 163.767437642,
            "count": 1,
            "index": 1
        },
        {
            "time": 164.019954649,
            "count": 1,
            "index": 4
        },
        {
            "time": 164.272471655,
            "count": 1,
            "index": 3
        },
        {
            "time": 164.524988662,
            "count": 1,
            "index": 1
        },
        {
            "time": 164.777505669,
            "count": 1,
            "index": 2
        },
        {
            "time": 165.030022676,
            "count": 1,
            "index": 3
        },
        {
            "time": 165.352199546,
            "count": 1,
            "index": 1
        },
        {
            "time": 165.604716553,
            "count": 1,
            "index": 4
        },
        {
            "time": 165.85723356,
            "count": 1,
            "index": 3
        },
        {
            "time": 166.109750567,
            "count": 1,
            "index": 4
        },
        {
            "time": 166.362267574,
            "count": 1,
            "index": 4
        },
        {
            "time": 166.61478458,
            "count": 1,
            "index": 3
        },
        {
            "time": 166.867301587,
            "count": 1,
            "index": 5
        },
        {
            "time": 167.410068027,
            "count": 1,
            "index": 1
        },
        {
            "time": 167.677097506,
            "count": 1,
            "index": 5
        },
        {
            "time": 168.074739229,
            "count": 1,
            "index": 3
        },
        {
            "time": 168.327256236,
            "count": 1,
            "index": 4
        },
        {
            "time": 168.579773243,
            "count": 1,
            "index": 5
        },
        {
            "time": 168.832290249,
            "count": 1,
            "index": 1
        },
        {
            "time": 169.084807256,
            "count": 1,
            "index": 1
        },
        {
            "time": 169.337324263,
            "count": 1,
            "index": 4
        },
        {
            "time": 169.58984127,
            "count": 1,
            "index": 4
        },
        {
            "time": 169.842358277,
            "count": 1,
            "index": 2
        },
        {
            "time": 170.094875283,
            "count": 1,
            "index": 4
        },
        {
            "time": 170.34739229,
            "count": 1,
            "index": 4
        },
        {
            "time": 170.942403628,
            "count": 1,
            "index": 2
        },
        {
            "time": 171.316825397,
            "count": 1,
            "index": 1
        },
        {
            "time": 171.569342404,
            "count": 1,
            "index": 4
        },
        {
            "time": 171.82185941,
            "count": 1,
            "index": 5
        },
        {
            "time": 172.074376417,
            "count": 1,
            "index": 4
        },
        {
            "time": 172.326893424,
            "count": 1,
            "index": 1
        },
        {
            "time": 172.579410431,
            "count": 1,
            "index": 1
        },
        {
            "time": 173.098956916,
            "count": 1,
            "index": 1
        },
        {
            "time": 173.351473923,
            "count": 1,
            "index": 4
        },
        {
            "time": 173.627210884,
            "count": 1,
            "index": 4
        },
        {
            "time": 173.879727891,
            "count": 1,
            "index": 1
        },
        {
            "time": 174.132244898,
            "count": 1,
            "index": 3
        },
        {
            "time": 174.434104308,
            "count": 1,
            "index": 3
        },
        {
            "time": 174.686621315,
            "count": 1,
            "index": 2
        },
        {
            "time": 174.939138322,
            "count": 1,
            "index": 1
        },
        {
            "time": 175.191655329,
            "count": 1,
            "index": 5
        },
        {
            "time": 175.444172336,
            "count": 1,
            "index": 4
        },
        {
            "time": 175.696689342,
            "count": 1,
            "index": 2
        },
        {
            "time": 176.216235828,
            "count": 1,
            "index": 2
        },
        {
            "time": 177.414965986,
            "count": 1,
            "index": 3
        },
        {
            "time": 177.667482993,
            "count": 1,
            "index": 3
        },
        {
            "time": 178.041904762,
            "count": 1,
            "index": 4
        },
        {
            "time": 178.384399093,
            "count": 1,
            "index": 3
        },
        {
            "time": 178.6369161,
            "count": 1,
            "index": 4
        },
        {
            "time": 179.208707483,
            "count": 1,
            "index": 3
        },
        {
            "time": 181.849977324,
            "count": 1,
            "index": 5
        },
        {
            "time": 182.102494331,
            "count": 1,
            "index": 2
        },
        {
            "time": 182.395646259,
            "count": 1,
            "index": 1
        },
        {
            "time": 182.784580499,
            "count": 1,
            "index": 4
        },
        {
            "time": 183.588571429,
            "count": 1,
            "index": 3
        },
        {
            "time": 183.841088435,
            "count": 1,
            "index": 1
        },
        {
            "time": 184.093605442,
            "count": 1,
            "index": 2
        },
        {
            "time": 184.346122449,
            "count": 1,
            "index": 1
        },
        {
            "time": 184.598639456,
            "count": 1,
            "index": 5
        },
        {
            "time": 184.851156463,
            "count": 1,
            "index": 2
        },
        {
            "time": 185.103673469,
            "count": 1,
            "index": 2
        },
        {
            "time": 185.356190476,
            "count": 1,
            "index": 5
        },
        {
            "time": 185.640634921,
            "count": 1,
            "index": 5
        },
        {
            "time": 185.893151927,
            "count": 1,
            "index": 5
        },
        {
            "time": 186.171791383,
            "count": 1,
            "index": 5
        },
        {
            "time": 186.42430839,
            "count": 1,
            "index": 5
        },
        {
            "time": 186.778412698,
            "count": 1,
            "index": 2
        },
        {
            "time": 187.030929705,
            "count": 1,
            "index": 2
        },
        {
            "time": 187.283446712,
            "count": 1,
            "index": 1
        },
        {
            "time": 187.535963719,
            "count": 1,
            "index": 1
        },
        {
            "time": 187.788480726,
            "count": 1,
            "index": 1
        },
        {
            "time": 188.040997732,
            "count": 1,
            "index": 2
        },
        {
            "time": 188.293514739,
            "count": 1,
            "index": 2
        },
        {
            "time": 189.271655329,
            "count": 1,
            "index": 5
        },
        {
            "time": 189.524172336,
            "count": 1,
            "index": 2
        },
        {
            "time": 189.776689342,
            "count": 1,
            "index": 4
        },
        {
            "time": 190.029206349,
            "count": 1,
            "index": 2
        },
        {
            "time": 190.281723356,
            "count": 1,
            "index": 4
        },
        {
            "time": 190.534240363,
            "count": 1,
            "index": 4
        },
        {
            "time": 190.78675737,
            "count": 1,
            "index": 5
        },
        {
            "time": 191.137959184,
            "count": 1,
            "index": 2
        },
        {
            "time": 192.168344671,
            "count": 1,
            "index": 1
        },
        {
            "time": 192.510839002,
            "count": 1,
            "index": 2
        },
        {
            "time": 192.763356009,
            "count": 1,
            "index": 5
        },
        {
            "time": 193.015873016,
            "count": 1,
            "index": 1
        },
        {
            "time": 193.384489796,
            "count": 1,
            "index": 2
        },
        {
            "time": 193.637006803,
            "count": 1,
            "index": 1
        },
        {
            "time": 193.88952381,
            "count": 1,
            "index": 3
        },
        {
            "time": 195.207256236,
            "count": 1,
            "index": 2
        },
        {
            "time": 195.459773243,
            "count": 1,
            "index": 3
        },
        {
            "time": 195.90675737,
            "count": 1,
            "index": 3
        },
        {
            "time": 196.678820862,
            "count": 1,
            "index": 5
        },
        {
            "time": 196.995192744,
            "count": 1,
            "index": 5
        },
        {
            "time": 197.247709751,
            "count": 1,
            "index": 2
        },
        {
            "time": 198.217142857,
            "count": 1,
            "index": 3
        },
        {
            "time": 198.469659864,
            "count": 1,
            "index": 4
        },
        {
            "time": 199.253333333,
            "count": 1,
            "index": 3
        },
        {
            "time": 199.578412698,
            "count": 1,
            "index": 1
        },
        {
            "time": 199.909297052,
            "count": 1,
            "index": 3
        },
        {
            "time": 200.602993197,
            "count": 1,
            "index": 1
        },
        {
            "time": 200.855510204,
            "count": 1,
            "index": 2
        },
        {
            "time": 201.108027211,
            "count": 1,
            "index": 4
        },
        {
            "time": 201.360544218,
            "count": 1,
            "index": 4
        },
        {
            "time": 201.613061224,
            "count": 1,
            "index": 1
        },
        {
            "time": 202.042630385,
            "count": 1,
            "index": 5
        },
        {
            "time": 202.60861678,
            "count": 1,
            "index": 1
        },
        {
            "time": 202.948208617,
            "count": 1,
            "index": 1
        },
        {
            "time": 203.200725624,
            "count": 1,
            "index": 4
        },
        {
            "time": 203.726077098,
            "count": 1,
            "index": 4
        },
        {
            "time": 203.978594104,
            "count": 1,
            "index": 3
        },
        {
            "time": 204.396553288,
            "count": 1,
            "index": 4
        },
        {
            "time": 204.657777778,
            "count": 1,
            "index": 1
        },
        {
            "time": 204.910294785,
            "count": 1,
            "index": 1
        },
        {
            "time": 205.162811791,
            "count": 1,
            "index": 1
        },
        {
            "time": 205.415328798,
            "count": 1,
            "index": 2
        },
        {
            "time": 205.667845805,
            "count": 1,
            "index": 5
        },
        {
            "time": 205.920362812,
            "count": 1,
            "index": 2
        },
        {
            "time": 206.172879819,
            "count": 1,
            "index": 5
        },
        {
            "time": 206.425396825,
            "count": 1,
            "index": 1
        },
        {
            "time": 206.721451247,
            "count": 1,
            "index": 1
        },
        {
            "time": 206.973968254,
            "count": 1,
            "index": 1
        },
        {
            "time": 207.226485261,
            "count": 1,
            "index": 1
        },
        {
            "time": 207.479002268,
            "count": 1,
            "index": 3
        },
        {
            "time": 208.341043084,
            "count": 1,
            "index": 3
        },
        {
            "time": 208.599365079,
            "count": 1,
            "index": 4
        },
        {
            "time": 209.002811791,
            "count": 1,
            "index": 1
        },
        {
            "time": 209.255328798,
            "count": 1,
            "index": 2
        },
        {
            "time": 209.522358277,
            "count": 1,
            "index": 5
        },
        {
            "time": 209.774875283,
            "count": 1,
            "index": 4
        },
        {
            "time": 210.02739229,
            "count": 1,
            "index": 1
        }
    ]
}